{
  "defaultSeason": "2025-26",
  "players": [
    {
      "id": "095972",
      "name": "홍유순",
      "team": "신한은행",
      "pos": "F",
      "height": "179 cm",
      "season": "2025-26",
      "gp": 1,
      "min": 38.3,
      "pts": 27.0,
      "reb": 12.0,
      "ast": 2.0,
      "stl": 0.0,
      "blk": 0.0,
      "fgp": 0.647,
      "tpp": 0.75,
      "ftp": 1.0
    },
    {
      "id": "095533",
      "name": "박지수",
      "team": "KB스타즈",
      "pos": "C",
      "height": "193 cm",
      "season": "2025-26",
      "gp": 1,
      "min": 27.2,
      "pts": 23.0,
      "reb": 11.0,
      "ast": 5.0,
      "stl": 0.0,
      "blk": 2.0,
      "fgp": 0.529,
      "tpp": 0.0,
      "ftp": 0.455
    },
    {
      "id": "095441",
      "name": "신지현",
      "team": "신한은행",
      "pos": "G",
      "height": "174 cm",
      "season": "2025-26",
      "gp": 1,
      "min": 29.5,
      "pts": 18.0,
      "reb": 3.0,
      "ast": 2.0,
      "stl": 2.0,
      "blk": 0.0,
      "fgp": 0.353,
      "tpp": 0.5,
      "ftp": 1.0
    },
    {
      "id": "095104",
      "name": "김단비",
      "team": "우리은행",
      "pos": "F",
      "height": "180 cm",
      "season": "2025-26",
      "gp": 1,
      "min": 34.2,
      "pts": 14.0,
      "reb": 15.0,
      "ast": 3.0,
      "stl": 2.0,
      "blk": 1.0,
      "fgp": 0.316,
      "tpp": 0.2,
      "ftp": 0.5
    },
    {
      "id": "095248",
      "name": "김소니아",
      "team": "BNK 썸",
      "pos": "F",
      "height": "178 cm",
      "season": "2025-26",
      "gp": 1,
      "min": 27.7,
      "pts": 14.0,
      "reb": 6.0,
      "ast": 3.0,
      "stl": 1.0,
      "blk": 0.0,
      "fgp": 0.556,
      "tpp": 1.0,
      "ftp": 0.75
    },
    {
      "id": "095899",
      "name": "김정은",
      "team": "BNK 썸",
      "pos": "F",
      "height": "177 cm",
      "season": "2025-26",
      "gp": 1,
      "min": 24.7,
      "pts": 14.0,
      "reb": 5.0,
      "ast": 0.0,
      "stl": 1.0,
      "blk": 0.0,
      "fgp": 0.556,
      "tpp": 0.5,
      "ftp": 0.667
    },
    {
      "id": "095788",
      "name": "박소희",
      "team": "하나은행",
      "pos": "G",
      "height": "178 cm",
      "season": "2025-26",
      "gp": 1,
      "min": 27.4,
      "pts": 14.0,
      "reb": 8.0,
      "ast": 1.0,
      "stl": 0.0,
      "blk": 0.0,
      "fgp": 0.385,
      "tpp": 0.333,
      "ftp": 0.5
    },
    {
      "id": "095749",
      "name": "조수아",
      "team": "삼성생명",
      "pos": "G",
      "height": "170 cm",
      "season": "2025-26",
      "gp": 1,
      "min": 27.0,
      "pts": 14.0,
      "reb": 3.0,
      "ast": 2.0,
      "stl": 1.0,
      "blk": 0.0,
      "fgp": 0.333,
      "tpp": 0.4,
      "ftp": 0.75
    },
    {
      "id": "095778",
      "name": "이해란",
      "team": "삼성생명",
      "pos": "F",
      "height": "182 cm",
      "season": "2025-26",
      "gp": 1,
      "min": 28.5,
      "pts": 13.0,
      "reb": 5.0,
      "ast": 2.0,
      "stl": 2.0,
      "blk": 1.0,
      "fgp": 0.429,
      "tpp": 0.0,
      "ftp": 0.333
    },
    {
      "id": "095477",
      "name": "김아름",
      "team": "삼성생명",
      "pos": "F",
      "height": "174 cm",
      "season": "2025-26",
      "gp": 1,
      "min": 25.1,
      "pts": 12.0,
      "reb": 2.0,
      "ast": 1.0,
      "stl": 0.0,
      "blk": 0.0,
      "fgp": 0.5,
      "tpp": 0.8,
      "ftp": 0
    },
    {
      "id": "095263",
      "name": "강이슬",
      "team": "KB스타즈",
      "pos": "F",
      "height": "180 cm",
      "season": "2025-26",
      "gp": 1,
      "min": 35.8,
      "pts": 11.0,
      "reb": 13.0,
      "ast": 3.0,
      "stl": 0.0,
      "blk": 1.0,
      "fgp": 0.294,
      "tpp": 0.167,
      "ftp": 0
    },
    {
      "id": "095633",
      "name": "신이슬",
      "team": "신한은행",
      "pos": "G",
      "height": "170 cm",
      "season": "2025-26",
      "gp": 1,
      "min": 33.5,
      "pts": 11.0,
      "reb": 14.0,
      "ast": 2.0,
      "stl": 0.0,
      "blk": 0.0,
      "fgp": 0.308,
      "tpp": 0.0,
      "ftp": 1.0
    },
    {
      "id": "096005",
      "name": "이민지",
      "team": "우리은행",
      "pos": "G",
      "height": "176 cm",
      "season": "2025-26",
      "gp": 1,
      "min": 35.0,
      "pts": 11.0,
      "reb": 5.0,
      "ast": 1.0,
      "stl": 1.0,
      "blk": 0.0,
      "fgp": 0.188,
      "tpp": 0.182,
      "ftp": 1.0
    },
    {
      "id": "095912",
      "name": "이이지마 사키",
      "team": "하나은행",
      "pos": "F",
      "height": "173 cm",
      "season": "2025-26",
      "gp": 1,
      "min": 28.0,
      "pts": 11.0,
      "reb": 6.0,
      "ast": 3.0,
      "stl": 1.0,
      "blk": 0.0,
      "fgp": 0.333,
      "tpp": 0.333,
      "ftp": 1.0
    },
    {
      "id": "095484",
      "name": "안혜지",
      "team": "BNK 썸",
      "pos": "G",
      "height": "165 cm",
      "season": "2025-26",
      "gp": 1,
      "min": 35.0,
      "pts": 10.0,
      "reb": 1.0,
      "ast": 5.0,
      "stl": 0.0,
      "blk": 0.0,
      "fgp": 0.455,
      "tpp": 0.0,
      "ftp": 0
    },
    {
      "id": "095499",
      "name": "진안",
      "team": "하나은행",
      "pos": "C",
      "height": "182 cm",
      "season": "2025-26",
      "gp": 1,
      "min": 29.5,
      "pts": 10.0,
      "reb": 6.0,
      "ast": 2.0,
      "stl": 0.0,
      "blk": 1.0,
      "fgp": 0.625,
      "tpp": 0,
      "ftp": 0.0
    },
    {
      "id": "096027",
      "name": "가와무라 미유키",
      "team": "삼성생명",
      "pos": "C",
      "height": "185 cm",
      "season": "2025-26",
      "gp": 1,
      "min": 21.9,
      "pts": 9.0,
      "reb": 3.0,
      "ast": 1.0,
      "stl": 0.0,
      "blk": 0.0,
      "fgp": 0.429,
      "tpp": 0.0,
      "ftp": 0.75
    },
    {
      "id": "096008",
      "name": "정현",
      "team": "하나은행",
      "pos": "F",
      "height": "178 cm",
      "season": "2025-26",
      "gp": 1,
      "min": 28.2,
      "pts": 9.0,
      "reb": 7.0,
      "ast": 0.0,
      "stl": 0.0,
      "blk": 1.0,
      "fgp": 0.273,
      "tpp": 0.4,
      "ftp": 0.5
    },
    {
      "id": "095710",
      "name": "허예은",
      "team": "KB스타즈",
      "pos": "G",
      "height": "165 cm",
      "season": "2025-26",
      "gp": 1,
      "min": 33.6,
      "pts": 9.0,
      "reb": 5.0,
      "ast": 9.0,
      "stl": 1.0,
      "blk": 0.0,
      "fgp": 0.273,
      "tpp": 0.25,
      "ftp": 0.5
    },
    {
      "id": "095482",
      "name": "김진영",
      "team": "신한은행",
      "pos": "F",
      "height": "177 cm",
      "season": "2025-26",
      "gp": 1,
      "min": 32.6,
      "pts": 8.0,
      "reb": 11.0,
      "ast": 4.0,
      "stl": 0.0,
      "blk": 0.0,
      "fgp": 0.222,
      "tpp": 0.333,
      "ftp": 0.5
    },
    {
      "id": "095715",
      "name": "정예림",
      "team": "하나은행",
      "pos": "G",
      "height": "175 cm",
      "season": "2025-26",
      "gp": 1,
      "min": 27.6,
      "pts": 8.0,
      "reb": 6.0,
      "ast": 1.0,
      "stl": 0.0,
      "blk": 1.0,
      "fgp": 0.5,
      "tpp": 0.5,
      "ftp": 1.0
    },
    {
      "id": "095186",
      "name": "박혜진",
      "team": "BNK 썸",
      "pos": "G",
      "height": "179 cm",
      "season": "2025-26",
      "gp": 1,
      "min": 31.1,
      "pts": 7.0,
      "reb": 11.0,
      "ast": 3.0,
      "stl": 5.0,
      "blk": 2.0,
      "fgp": 0.25,
      "tpp": 0.333,
      "ftp": 1.0
    },
    {
      "id": "095830",
      "name": "고서연",
      "team": "하나은행",
      "pos": "G",
      "height": "172 cm",
      "season": "2025-26",
      "gp": 1,
      "min": 25.0,
      "pts": 6.0,
      "reb": 9.0,
      "ast": 3.0,
      "stl": 1.0,
      "blk": 0.0,
      "fgp": 0.333,
      "tpp": 0.4,
      "ftp": 0
    },
    {
      "id": "095832",
      "name": "박진영",
      "team": "하나은행",
      "pos": "F",
      "height": "178 cm",
      "season": "2025-26",
      "gp": 1,
      "min": 20.2,
      "pts": 6.0,
      "reb": 3.0,
      "ast": 0.0,
      "stl": 0.0,
      "blk": 2.0,
      "fgp": 0.2,
      "tpp": 0.0,
      "ftp": 1.0
    },
    {
      "id": "095780",
      "name": "변소정",
      "team": "BNK 썸",
      "pos": "F",
      "height": "180 cm",
      "season": "2025-26",
      "gp": 1,
      "min": 24.8,
      "pts": 6.0,
      "reb": 2.0,
      "ast": 3.0,
      "stl": 0.0,
      "blk": 0.0,
      "fgp": 0.375,
      "tpp": 0,
      "ftp": 0
    },
    {
      "id": "096033",
      "name": "사카이 사라",
      "team": "KB스타즈",
      "pos": "G",
      "height": "164 cm",
      "season": "2025-26",
      "gp": 1,
      "min": 29.5,
      "pts": 6.0,
      "reb": 3.0,
      "ast": 1.0,
      "stl": 0.0,
      "blk": 0.0,
      "fgp": 0.222,
      "tpp": 0.333,
      "ftp": 0
    },
    {
      "id": "095746",
      "name": "양지수",
      "team": "KB스타즈",
      "pos": "F",
      "height": "174 cm",
      "season": "2025-26",
      "gp": 1,
      "min": 18.4,
      "pts": 6.0,
      "reb": 2.0,
      "ast": 0.0,
      "stl": 1.0,
      "blk": 0.0,
      "fgp": 0.333,
      "tpp": 0.4,
      "ftp": 0
    },
    {
      "id": "095703",
      "name": "이명관",
      "team": "우리은행",
      "pos": "F",
      "height": "173 cm",
      "season": "2025-26",
      "gp": 1,
      "min": 33.3,
      "pts": 6.0,
      "reb": 11.0,
      "ast": 1.0,
      "stl": 2.0,
      "blk": 0.0,
      "fgp": 0.222,
      "tpp": 0.0,
      "ftp": 1.0
    },
    {
      "id": "095636",
      "name": "이소희",
      "team": "BNK 썸",
      "pos": "G",
      "height": "171 cm",
      "season": "2025-26",
      "gp": 1,
      "min": 32.6,
      "pts": 6.0,
      "reb": 7.0,
      "ast": 5.0,
      "stl": 2.0,
      "blk": 0.0,
      "fgp": 0.222,
      "tpp": 0.2,
      "ftp": 1.0
    },
    {
      "id": "095210",
      "name": "심성영",
      "team": "우리은행",
      "pos": "G",
      "height": "165 cm",
      "season": "2025-26",
      "gp": 1,
      "min": 13.9,
      "pts": 5.0,
      "reb": 1.0,
      "ast": 1.0,
      "stl": 0.0,
      "blk": 0.0,
      "fgp": 0.25,
      "tpp": 0.167,
      "ftp": 0
    },
    {
      "id": "095637",
      "name": "이채은",
      "team": "KB스타즈",
      "pos": "G",
      "height": "171 cm",
      "season": "2025-26",
      "gp": 1,
      "min": 25.3,
      "pts": 5.0,
      "reb": 3.0,
      "ast": 1.0,
      "stl": 0.0,
      "blk": 0.0,
      "fgp": 1.0,
      "tpp": 1.0,
      "ftp": 0
    },
    {
      "id": "095261",
      "name": "최이샘",
      "team": "신한은행",
      "pos": "F",
      "height": "182 cm",
      "season": "2025-26",
      "gp": 1,
      "min": 7.3,
      "pts": 5.0,
      "reb": 2.0,
      "ast": 0.0,
      "stl": 0.0,
      "blk": 0.0,
      "fgp": 0.5,
      "tpp": 0.0,
      "ftp": 1.0
    },
    {
      "id": "096028",
      "name": "하마니시 나나미",
      "team": "삼성생명",
      "pos": "G",
      "height": "168 cm",
      "season": "2025-26",
      "gp": 1,
      "min": 20.0,
      "pts": 5.0,
      "reb": 2.0,
      "ast": 6.0,
      "stl": 1.0,
      "blk": 1.0,
      "fgp": 0.4,
      "tpp": 0.333,
      "ftp": 0
    },
    {
      "id": "095543",
      "name": "나윤정",
      "team": "KB스타즈",
      "pos": "F",
      "height": "172 cm",
      "season": "2025-26",
      "gp": 1,
      "min": 7.8,
      "pts": 4.0,
      "reb": 1.0,
      "ast": 0.0,
      "stl": 0.0,
      "blk": 0.0,
      "fgp": 0.25,
      "tpp": 0.0,
      "ftp": 1.0
    },
    {
      "id": "095115",
      "name": "배혜윤",
      "team": "삼성생명",
      "pos": "C",
      "height": "183 cm",
      "season": "2025-26",
      "gp": 1,
      "min": 10.1,
      "pts": 4.0,
      "reb": 3.0,
      "ast": 0.0,
      "stl": 0.0,
      "blk": 0.0,
      "fgp": 0.5,
      "tpp": 0,
      "ftp": 1.0
    },
    {
      "id": "095825",
      "name": "심수현",
      "team": "BNK 썸",
      "pos": "G",
      "height": "165 cm",
      "season": "2025-26",
      "gp": 1,
      "min": 5.3,
      "pts": 4.0,
      "reb": 1.0,
      "ast": 0.0,
      "stl": 0.0,
      "blk": 0.0,
      "fgp": 0.667,
      "tpp": 0,
      "ftp": 0
    },
    {
      "id": "095700",
      "name": "고나연",
      "team": "신한은행",
      "pos": "F",
      "height": "173 cm",
      "season": "2025-26",
      "gp": 1,
      "min": 27.3,
      "pts": 3.0,
      "reb": 3.0,
      "ast": 2.0,
      "stl": 3.0,
      "blk": 0.0,
      "fgp": 0.1,
      "tpp": 0.143,
      "ftp": 0
    },
    {
      "id": "095450",
      "name": "강계리",
      "team": "우리은행",
      "pos": "G",
      "height": "164 cm",
      "season": "2025-26",
      "gp": 1,
      "min": 17.6,
      "pts": 2.0,
      "reb": 0.0,
      "ast": 2.0,
      "stl": 0.0,
      "blk": 0.0,
      "fgp": 0.0,
      "tpp": 0.0,
      "ftp": 1.0
    },
    {
      "id": "095713",
      "name": "강유림",
      "team": "삼성생명",
      "pos": "F",
      "height": "175 cm",
      "season": "2025-26",
      "gp": 1,
      "min": 26.4,
      "pts": 2.0,
      "reb": 3.0,
      "ast": 1.0,
      "stl": 2.0,
      "blk": 0.0,
      "fgp": 0.167,
      "tpp": 0.0,
      "ftp": 0
    },
    {
      "id": "095041",
      "name": "김정은",
      "team": "하나은행",
      "pos": "F",
      "height": "179 cm",
      "season": "2025-26",
      "gp": 1,
      "min": 12.9,
      "pts": 2.0,
      "reb": 3.0,
      "ast": 3.0,
      "stl": 1.0,
      "blk": 0.0,
      "fgp": 0.25,
      "tpp": 0.0,
      "ftp": 0
    },
    {
      "id": "095833",
      "name": "박성진",
      "team": "BNK 썸",
      "pos": "C",
      "height": "184 cm",
      "season": "2025-26",
      "gp": 1,
      "min": 9.9,
      "pts": 2.0,
      "reb": 2.0,
      "ast": 0.0,
      "stl": 0.0,
      "blk": 0.0,
      "fgp": 0.5,
      "tpp": 0,
      "ftp": 0
    },
    {
      "id": "095444",
      "name": "박혜미",
      "team": "우리은행",
      "pos": "F",
      "height": "182 cm",
      "season": "2025-26",
      "gp": 1,
      "min": 8.7,
      "pts": 2.0,
      "reb": 2.0,
      "ast": 0.0,
      "stl": 0.0,
      "blk": 0.0,
      "fgp": 0.333,
      "tpp": 0.0,
      "ftp": 0
    },
    {
      "id": "096030",
      "name": "세키 나나미",
      "team": "우리은행",
      "pos": "G",
      "height": "171 cm",
      "season": "2025-26",
      "gp": 1,
      "min": 28.3,
      "pts": 2.0,
      "reb": 5.0,
      "ast": 1.0,
      "stl": 0.0,
      "blk": 0.0,
      "fgp": 0.083,
      "tpp": 0.0,
      "ftp": 0
    },
    {
      "id": "096031",
      "name": "오니즈카 아야노",
      "team": "우리은행",
      "pos": "G",
      "height": "168 cm",
      "season": "2025-26",
      "gp": 1,
      "min": 12.8,
      "pts": 2.0,
      "reb": 1.0,
      "ast": 0.0,
      "stl": 0.0,
      "blk": 0.0,
      "fgp": 0.167,
      "tpp": 0.0,
      "ftp": 0
    },
    {
      "id": "095826",
      "name": "이두나",
      "team": "신한은행",
      "pos": "F",
      "height": "173 cm",
      "season": "2025-26",
      "gp": 1,
      "min": 13.3,
      "pts": 2.0,
      "reb": 0.0,
      "ast": 0.0,
      "stl": 0.0,
      "blk": 0.0,
      "fgp": 0.2,
      "tpp": 0,
      "ftp": 0
    },
    {
      "id": "096135",
      "name": "이원정",
      "team": "BNK 썸",
      "pos": "G",
      "height": "172 cm",
      "season": "2025-26",
      "gp": 1,
      "min": 3.4,
      "pts": 2.0,
      "reb": 0.0,
      "ast": 1.0,
      "stl": 0.0,
      "blk": 0.0,
      "fgp": 0.5,
      "tpp": 0,
      "ftp": 0
    },
    {
      "id": "096002",
      "name": "최예슬",
      "team": "삼성생명",
      "pos": "F",
      "height": "180 cm",
      "season": "2025-26",
      "gp": 1,
      "min": 18.0,
      "pts": 2.0,
      "reb": 4.0,
      "ast": 1.0,
      "stl": 0.0,
      "blk": 0.0,
      "fgp": 0.333,
      "tpp": 0.0,
      "ftp": 0
    },
    {
      "id": "095915",
      "name": "히라노 미츠키",
      "team": "신한은행",
      "pos": "G",
      "height": "166 cm",
      "season": "2025-26",
      "gp": 1,
      "min": 14.6,
      "pts": 2.0,
      "reb": 3.0,
      "ast": 5.0,
      "stl": 1.0,
      "blk": 0.0,
      "fgp": 0.25,
      "tpp": 0.0,
      "ftp": 0
    },
    {
      "id": "096138",
      "name": "고리미",
      "team": "KB스타즈",
      "pos": "F",
      "height": "175 cm",
      "season": "2025-26",
      "gp": 1,
      "min": 0.6,
      "pts": 0.0,
      "reb": 0.0,
      "ast": 0.0,
      "stl": 0.0,
      "blk": 0.0,
      "fgp": 0,
      "tpp": 0,
      "ftp": 0
    },
    {
      "id": "095901",
      "name": "고현지",
      "team": "KB스타즈",
      "pos": "F",
      "height": "182 cm",
      "season": "2025-26",
      "gp": 1,
      "min": 0.6,
      "pts": 0.0,
      "reb": 0.0,
      "ast": 0.0,
      "stl": 0.0,
      "blk": 0.0,
      "fgp": 0,
      "tpp": 0,
      "ftp": 0
    },
    {
      "id": "095226",
      "name": "김단비",
      "team": "삼성생명",
      "pos": "F",
      "height": "175 cm",
      "season": "2025-26",
      "gp": 0,
      "min": 0.0,
      "pts": 0.0,
      "reb": 0.0,
      "ast": 0.0,
      "stl": 0.0,
      "blk": 0.0,
      "fgp": 0,
      "tpp": 0,
      "ftp": 0
    },
    {
      "id": "096001",
      "name": "김도연",
      "team": "BNK 썸",
      "pos": "C",
      "height": "186 cm",
      "season": "2025-26",
      "gp": 0,
      "min": 0.0,
      "pts": 0.0,
      "reb": 0.0,
      "ast": 0.0,
      "stl": 0.0,
      "blk": 0.0,
      "fgp": 0,
      "tpp": 0,
      "ftp": 0
    },
    {
      "id": "096137",
      "name": "김민경",
      "team": "KB스타즈",
      "pos": "C",
      "height": "183 cm",
      "season": "2025-26",
      "gp": 0,
      "min": 0.0,
      "pts": 0.0,
      "reb": 0.0,
      "ast": 0.0,
      "stl": 0.0,
      "blk": 0.0,
      "fgp": 0,
      "tpp": 0,
      "ftp": 0
    },
    {
      "id": "095834",
      "name": "김민아",
      "team": "BNK 썸",
      "pos": "G",
      "height": "170 cm",
      "season": "2025-26",
      "gp": 1,
      "min": 4.1,
      "pts": 0.0,
      "reb": 0.0,
      "ast": 0.0,
      "stl": 0.0,
      "blk": 0.0,
      "fgp": 0,
      "tpp": 0,
      "ftp": 0
    },
    {
      "id": "095251",
      "name": "김민정",
      "team": "KB스타즈",
      "pos": "F",
      "height": "181 cm",
      "season": "2025-26",
      "gp": 0,
      "min": 0.0,
      "pts": 0.0,
      "reb": 0.0,
      "ast": 0.0,
      "stl": 0.0,
      "blk": 0.0,
      "fgp": 0,
      "tpp": 0,
      "ftp": 0
    },
    {
      "id": "096000",
      "name": "김보현",
      "team": "BNK 썸",
      "pos": "G",
      "height": "174 cm",
      "season": "2025-26",
      "gp": 0,
      "min": 0.0,
      "pts": 0.0,
      "reb": 0.0,
      "ast": 0.0,
      "stl": 0.0,
      "blk": 0.0,
      "fgp": 0,
      "tpp": 0,
      "ftp": 0
    },
    {
      "id": "095909",
      "name": "김솔",
      "team": "우리은행",
      "pos": "G",
      "height": "174 cm",
      "season": "2025-26",
      "gp": 0,
      "min": 0.0,
      "pts": 0.0,
      "reb": 0.0,
      "ast": 0.0,
      "stl": 0.0,
      "blk": 0.0,
      "fgp": 0,
      "tpp": 0,
      "ftp": 0
    },
    {
      "id": "095442",
      "name": "김시온",
      "team": "하나은행",
      "pos": "G",
      "height": "177 cm",
      "season": "2025-26",
      "gp": 0,
      "min": 0.0,
      "pts": 0.0,
      "reb": 0.0,
      "ast": 0.0,
      "stl": 0.0,
      "blk": 0.0,
      "fgp": 0,
      "tpp": 0,
      "ftp": 0
    },
    {
      "id": "096148",
      "name": "김연진",
      "team": "하나은행",
      "pos": "F",
      "height": "176 cm",
      "season": "2025-26",
      "gp": 0,
      "min": 0.0,
      "pts": 0.0,
      "reb": 0.0,
      "ast": 0.0,
      "stl": 0.0,
      "blk": 0.0,
      "fgp": 0,
      "tpp": 0,
      "ftp": 0
    },
    {
      "id": "095504",
      "name": "김예진",
      "team": "우리은행",
      "pos": "F",
      "height": "174 cm",
      "season": "2025-26",
      "gp": 1,
      "min": 10.4,
      "pts": 0.0,
      "reb": 2.0,
      "ast": 0.0,
      "stl": 0.0,
      "blk": 0.0,
      "fgp": 0.0,
      "tpp": 0.0,
      "ftp": 0
    },
    {
      "id": "095781",
      "name": "김은선",
      "team": "KB스타즈",
      "pos": "G",
      "height": "169 cm",
      "season": "2025-26",
      "gp": 0,
      "min": 0.0,
      "pts": 0.0,
      "reb": 0.0,
      "ast": 0.0,
      "stl": 0.0,
      "blk": 0.0,
      "fgp": 0,
      "tpp": 0,
      "ftp": 0
    },
    {
      "id": "095503",
      "name": "김지영",
      "team": "신한은행",
      "pos": "G",
      "height": "172 cm",
      "season": "2025-26",
      "gp": 0,
      "min": 0.0,
      "pts": 0.0,
      "reb": 0.0,
      "ast": 0.0,
      "stl": 0.0,
      "blk": 0.0,
      "fgp": 0,
      "tpp": 0,
      "ftp": 0
    },
    {
      "id": "096004",
      "name": "김채은",
      "team": "신한은행",
      "pos": "C",
      "height": "186 cm",
      "season": "2025-26",
      "gp": 0,
      "min": 0.0,
      "pts": 0.0,
      "reb": 0.0,
      "ast": 0.0,
      "stl": 0.0,
      "blk": 0.0,
      "fgp": 0,
      "tpp": 0,
      "ftp": 0
    },
    {
      "id": "095836",
      "name": "노혜경",
      "team": "KB스타즈",
      "pos": "F",
      "height": "178 cm",
      "season": "2025-26",
      "gp": 0,
      "min": 0.0,
      "pts": 0.0,
      "reb": 0.0,
      "ast": 0.0,
      "stl": 0.0,
      "blk": 0.0,
      "fgp": 0,
      "tpp": 0,
      "ftp": 0
    },
    {
      "id": "096029",
      "name": "미마 루이",
      "team": "신한은행",
      "pos": "C",
      "height": "185 cm",
      "season": "2025-26",
      "gp": 0,
      "min": 0.0,
      "pts": 0.0,
      "reb": 0.0,
      "ast": 0.0,
      "stl": 0.0,
      "blk": 0.0,
      "fgp": 0,
      "tpp": 0,
      "ftp": 0
    },
    {
      "id": "095900",
      "name": "박다원",
      "team": "BNK 썸",
      "pos": "F",
      "height": "179 cm",
      "season": "2025-26",
      "gp": 0,
      "min": 0.0,
      "pts": 0.0,
      "reb": 0.0,
      "ast": 0.0,
      "stl": 0.0,
      "blk": 0.0,
      "fgp": 0,
      "tpp": 0,
      "ftp": 0
    },
    {
      "id": "096145",
      "name": "박소영",
      "team": "우리은행",
      "pos": "G",
      "height": "165 cm",
      "season": "2025-26",
      "gp": 0,
      "min": 0.0,
      "pts": 0.0,
      "reb": 0.0,
      "ast": 0.0,
      "stl": 0.0,
      "blk": 0.0,
      "fgp": 0,
      "tpp": 0,
      "ftp": 0
    },
    {
      "id": "096136",
      "name": "박지수",
      "team": "BNK 썸",
      "pos": "F",
      "height": "177 cm",
      "season": "2025-26",
      "gp": 0,
      "min": 0.0,
      "pts": 0.0,
      "reb": 0.0,
      "ast": 0.0,
      "stl": 0.0,
      "blk": 0.0,
      "fgp": 0,
      "tpp": 0,
      "ftp": 0
    },
    {
      "id": "095782",
      "name": "방지온",
      "team": "삼성생명",
      "pos": "C",
      "height": "183 cm",
      "season": "2025-26",
      "gp": 0,
      "min": 0.0,
      "pts": 0.0,
      "reb": 0.0,
      "ast": 0.0,
      "stl": 0.0,
      "blk": 0.0,
      "fgp": 0,
      "tpp": 0,
      "ftp": 0
    },
    {
      "id": "095908",
      "name": "변하정",
      "team": "우리은행",
      "pos": "F",
      "height": "180 cm",
      "season": "2025-26",
      "gp": 1,
      "min": 5.8,
      "pts": 0.0,
      "reb": 0.0,
      "ast": 0.0,
      "stl": 1.0,
      "blk": 0.0,
      "fgp": 0,
      "tpp": 0,
      "ftp": 0
    },
    {
      "id": "095902",
      "name": "성수연",
      "team": "KB스타즈",
      "pos": "G",
      "height": "165 cm",
      "season": "2025-26",
      "gp": 1,
      "min": 7.8,
      "pts": 0.0,
      "reb": 1.0,
      "ast": 0.0,
      "stl": 0.0,
      "blk": 0.0,
      "fgp": 0.0,
      "tpp": 0.0,
      "ftp": 0
    },
    {
      "id": "095999",
      "name": "송윤하",
      "team": "KB스타즈",
      "pos": "C",
      "height": "179 cm",
      "season": "2025-26",
      "gp": 1,
      "min": 12.8,
      "pts": 0.0,
      "reb": 3.0,
      "ast": 1.0,
      "stl": 0.0,
      "blk": 3.0,
      "fgp": 0.0,
      "tpp": 0,
      "ftp": 0
    },
    {
      "id": "095919",
      "name": "스나가와 나츠키",
      "team": "BNK 썸",
      "pos": "G",
      "height": "162 cm",
      "season": "2025-26",
      "gp": 1,
      "min": 1.4,
      "pts": 0.0,
      "reb": 0.0,
      "ast": 0.0,
      "stl": 0.0,
      "blk": 0.0,
      "fgp": 0,
      "tpp": 0,
      "ftp": 0
    },
    {
      "id": "095259",
      "name": "양인영",
      "team": "하나은행",
      "pos": "C",
      "height": "184 cm",
      "season": "2025-26",
      "gp": 0,
      "min": 0.0,
      "pts": 0.0,
      "reb": 0.0,
      "ast": 0.0,
      "stl": 0.0,
      "blk": 0.0,
      "fgp": 0,
      "tpp": 0,
      "ftp": 0
    },
    {
      "id": "096140",
      "name": "양혜은",
      "team": "삼성생명",
      "pos": "C",
      "height": "178 cm",
      "season": "2025-26",
      "gp": 0,
      "min": 0.0,
      "pts": 0.0,
      "reb": 0.0,
      "ast": 0.0,
      "stl": 0.0,
      "blk": 0.0,
      "fgp": 0,
      "tpp": 0,
      "ftp": 0
    },
    {
      "id": "095037",
      "name": "염윤아",
      "team": "KB스타즈",
      "pos": "G",
      "height": "177 cm",
      "season": "2025-26",
      "gp": 0,
      "min": 0.0,
      "pts": 0.0,
      "reb": 0.0,
      "ast": 0.0,
      "stl": 0.0,
      "blk": 0.0,
      "fgp": 0,
      "tpp": 0,
      "ftp": 0
    },
    {
      "id": "095707",
      "name": "오승인",
      "team": "우리은행",
      "pos": "F",
      "height": "183 cm",
      "season": "2025-26",
      "gp": 0,
      "min": 0.0,
      "pts": 0.0,
      "reb": 0.0,
      "ast": 0.0,
      "stl": 0.0,
      "blk": 0.0,
      "fgp": 0,
      "tpp": 0,
      "ftp": 0
    },
    {
      "id": "095254",
      "name": "유승희",
      "team": "우리은행",
      "pos": "G",
      "height": "175 cm",
      "season": "2025-26",
      "gp": 0,
      "min": 0.0,
      "pts": 0.0,
      "reb": 0.0,
      "ast": 0.0,
      "stl": 0.0,
      "blk": 0.0,
      "fgp": 0,
      "tpp": 0,
      "ftp": 0
    },
    {
      "id": "096003",
      "name": "유하은",
      "team": "삼성생명",
      "pos": "F",
      "height": "178 cm",
      "season": "2025-26",
      "gp": 1,
      "min": 4.0,
      "pts": 0.0,
      "reb": 0.0,
      "ast": 0.0,
      "stl": 0.0,
      "blk": 0.0,
      "fgp": 0.0,
      "tpp": 0.0,
      "ftp": 0
    },
    {
      "id": "095497",
      "name": "윤예빈",
      "team": "삼성생명",
      "pos": "G",
      "height": "180 cm",
      "season": "2025-26",
      "gp": 0,
      "min": 0.0,
      "pts": 0.0,
      "reb": 0.0,
      "ast": 0.0,
      "stl": 0.0,
      "blk": 0.0,
      "fgp": 0,
      "tpp": 0,
      "ftp": 0
    },
    {
      "id": "096143",
      "name": "이가현",
      "team": "신한은행",
      "pos": "F",
      "height": "180 cm",
      "season": "2025-26",
      "gp": 0,
      "min": 0.0,
      "pts": 0.0,
      "reb": 0.0,
      "ast": 0.0,
      "stl": 0.0,
      "blk": 0.0,
      "fgp": 0,
      "tpp": 0,
      "ftp": 0
    },
    {
      "id": "095742",
      "name": "이다연",
      "team": "우리은행",
      "pos": "F",
      "height": "175 cm",
      "season": "2025-26",
      "gp": 0,
      "min": 0.0,
      "pts": 0.0,
      "reb": 0.0,
      "ast": 0.0,
      "stl": 0.0,
      "blk": 0.0,
      "fgp": 0,
      "tpp": 0,
      "ftp": 0
    },
    {
      "id": "095831",
      "name": "이다현",
      "team": "하나은행",
      "pos": "F",
      "height": "179 cm",
      "season": "2025-26",
      "gp": 1,
      "min": 1.3,
      "pts": 0.0,
      "reb": 1.0,
      "ast": 0.0,
      "stl": 0.0,
      "blk": 0.0,
      "fgp": 0.0,
      "tpp": 0,
      "ftp": 0
    },
    {
      "id": "095978",
      "name": "이여명",
      "team": "KB스타즈",
      "pos": "G",
      "height": "162 cm",
      "season": "2025-26",
      "gp": 1,
      "min": 0.6,
      "pts": 0.0,
      "reb": 0.0,
      "ast": 0.0,
      "stl": 0.0,
      "blk": 0.0,
      "fgp": 0,
      "tpp": 0,
      "ftp": 0
    },
    {
      "id": "095904",
      "name": "이예나",
      "team": "삼성생명",
      "pos": "F",
      "height": "179 cm",
      "season": "2025-26",
      "gp": 1,
      "min": 6.7,
      "pts": 0.0,
      "reb": 0.0,
      "ast": 0.0,
      "stl": 0.0,
      "blk": 0.0,
      "fgp": 0.0,
      "tpp": 0,
      "ftp": 0
    },
    {
      "id": "095642",
      "name": "이윤미",
      "team": "KB스타즈",
      "pos": "F",
      "height": "172 cm",
      "season": "2025-26",
      "gp": 0,
      "min": 0.0,
      "pts": 0.0,
      "reb": 0.0,
      "ast": 0.0,
      "stl": 0.0,
      "blk": 0.0,
      "fgp": 0,
      "tpp": 0,
      "ftp": 0
    },
    {
      "id": "096147",
      "name": "이은서",
      "team": "하나은행",
      "pos": "G",
      "height": "172 cm",
      "season": "2025-26",
      "gp": 0,
      "min": 0.0,
      "pts": 0.0,
      "reb": 0.0,
      "ast": 0.0,
      "stl": 0.0,
      "blk": 0.0,
      "fgp": 0,
      "tpp": 0,
      "ftp": 0
    },
    {
      "id": "095524",
      "name": "이주연",
      "team": "삼성생명",
      "pos": "G",
      "height": "171 cm",
      "season": "2025-26",
      "gp": 1,
      "min": 12.4,
      "pts": 0.0,
      "reb": 1.0,
      "ast": 0.0,
      "stl": 2.0,
      "blk": 0.0,
      "fgp": 0.0,
      "tpp": 0.0,
      "ftp": 0
    },
    {
      "id": "095527",
      "name": "이혜미",
      "team": "신한은행",
      "pos": "G",
      "height": "170 cm",
      "season": "2025-26",
      "gp": 1,
      "min": 2.7,
      "pts": 0.0,
      "reb": 0.0,
      "ast": 0.0,
      "stl": 0.0,
      "blk": 0.0,
      "fgp": 0,
      "tpp": 0,
      "ftp": 0
    },
    {
      "id": "095779",
      "name": "임규리",
      "team": "삼성생명",
      "pos": "F",
      "height": "183 cm",
      "season": "2025-26",
      "gp": 0,
      "min": 0.0,
      "pts": 0.0,
      "reb": 0.0,
      "ast": 0.0,
      "stl": 0.0,
      "blk": 0.0,
      "fgp": 0,
      "tpp": 0,
      "ftp": 0
    },
    {
      "id": "096141",
      "name": "정채련",
      "team": "신한은행",
      "pos": "G",
      "height": "161 cm",
      "season": "2025-26",
      "gp": 0,
      "min": 0.0,
      "pts": 0.0,
      "reb": 0.0,
      "ast": 0.0,
      "stl": 0.0,
      "blk": 0.0,
      "fgp": 0,
      "tpp": 0,
      "ftp": 0
    },
    {
      "id": "095784",
      "name": "최민주",
      "team": "BNK 썸",
      "pos": "C",
      "height": "180 cm",
      "season": "2025-26",
      "gp": 0,
      "min": 0.0,
      "pts": 0.0,
      "reb": 0.0,
      "ast": 0.0,
      "stl": 0.0,
      "blk": 0.0,
      "fgp": 0,
      "tpp": 0,
      "ftp": 0
    },
    {
      "id": "095716",
      "name": "최서연",
      "team": "BNK 썸",
      "pos": "G",
      "height": "170 cm",
      "season": "2025-26",
      "gp": 0,
      "min": 0.0,
      "pts": 0.0,
      "reb": 0.0,
      "ast": 0.0,
      "stl": 0.0,
      "blk": 0.0,
      "fgp": 0,
      "tpp": 0,
      "ftp": 0
    },
    {
      "id": "096144",
      "name": "최예원",
      "team": "우리은행",
      "pos": "F",
      "height": "178 cm",
      "season": "2025-26",
      "gp": 0,
      "min": 0.0,
      "pts": 0.0,
      "reb": 0.0,
      "ast": 0.0,
      "stl": 0.0,
      "blk": 0.0,
      "fgp": 0,
      "tpp": 0,
      "ftp": 0
    },
    {
      "id": "095740",
      "name": "편선우",
      "team": "우리은행",
      "pos": "F",
      "height": "178 cm",
      "season": "2025-26",
      "gp": 0,
      "min": 0.0,
      "pts": 0.0,
      "reb": 0.0,
      "ast": 0.0,
      "stl": 0.0,
      "blk": 0.0,
      "fgp": 0,
      "tpp": 0,
      "ftp": 0
    },
    {
      "id": "096007",
      "name": "하지윤",
      "team": "하나은행",
      "pos": "G",
      "height": "167 cm",
      "season": "2025-26",
      "gp": 0,
      "min": 0.0,
      "pts": 0.0,
      "reb": 0.0,
      "ast": 0.0,
      "stl": 0.0,
      "blk": 0.0,
      "fgp": 0,
      "tpp": 0,
      "ftp": 0
    },
    {
      "id": "095528",
      "name": "한엄지",
      "team": "우리은행",
      "pos": "F",
      "height": "180 cm",
      "season": "2025-26",
      "gp": 0,
      "min": 0.0,
      "pts": 0.0,
      "reb": 0.0,
      "ast": 0.0,
      "stl": 0.0,
      "blk": 0.0,
      "fgp": 0,
      "tpp": 0,
      "ftp": 0
    },
    {
      "id": "096139",
      "name": "한지민",
      "team": "삼성생명",
      "pos": "F",
      "height": "172 cm",
      "season": "2025-26",
      "gp": 0,
      "min": 0.0,
      "pts": 0.0,
      "reb": 0.0,
      "ast": 0.0,
      "stl": 0.0,
      "blk": 0.0,
      "fgp": 0,
      "tpp": 0,
      "ftp": 0
    },
    {
      "id": "095905",
      "name": "허유정",
      "team": "신한은행",
      "pos": "G",
      "height": "173 cm",
      "season": "2025-26",
      "gp": 1,
      "min": 0.9,
      "pts": 0.0,
      "reb": 0.0,
      "ast": 0.0,
      "stl": 0.0,
      "blk": 0.0,
      "fgp": 0,
      "tpp": 0,
      "ftp": 0
    },
    {
      "id": "096146",
      "name": "황윤서",
      "team": "하나은행",
      "pos": "F",
      "height": "182 cm",
      "season": "2025-26",
      "gp": 0,
      "min": 0.0,
      "pts": 0.0,
      "reb": 0.0,
      "ast": 0.0,
      "stl": 0.0,
      "blk": 0.0,
      "fgp": 0,
      "tpp": 0,
      "ftp": 0
    },
    {
      "id": "096142",
      "name": "황현정",
      "team": "신한은행",
      "pos": "G",
      "height": "170 cm",
      "season": "2025-26",
      "gp": 0,
      "min": 0.0,
      "pts": 0.0,
      "reb": 0.0,
      "ast": 0.0,
      "stl": 0.0,
      "blk": 0.0,
      "fgp": 0,
      "tpp": 0,
      "ftp": 0
    }
  ]
}